latticex/__init__.py
latticex/_rosetta.cpython-36m-x86_64-linux-gnu.so
latticex/libcommon.so
latticex/libmpc-comm.so
latticex/libmpc-io.so
latticex/libmpc-naive.so
latticex/libmpc-snn.so
latticex/libprotocol-api.so
latticex/libprotocol-base.so
latticex/librtt-ops.so
latticex/libsecure-ops.so
latticex/libtf-dpass.so
latticex/rosetta/__init__.py
latticex/rosetta/controller/__init__.py
latticex/rosetta/controller/backend_handler.py
latticex/rosetta/controller/common_util.py
latticex/rosetta/controller/controller_base_.py
latticex/rosetta/controller/dataset_api.py
latticex/rosetta/controller/input_api.py
latticex/rosetta/controller/protocol_api.py
latticex/rosetta/controller/random_api.py
latticex/rosetta/rtt/__init__.py
latticex/rosetta/rtt/framework/__init__.py
latticex/rosetta/rtt/framework/constant_op.py
latticex/rosetta/rtt/framework/rtt_tensor.py
latticex/rosetta/rtt/grads_ops/__init__.py
latticex/rosetta/rtt/grads_ops/convert_grad.py
latticex/rosetta/rtt/ops/__init__.py
latticex/rosetta/rtt/ops/array_ops.py
latticex/rosetta/rtt/ops/gradients_util.py
latticex/rosetta/rtt/ops/resource_variable_ops.py
latticex/rosetta/rtt/ops/rtt_math_ops.py
latticex/rosetta/rtt/ops/state_ops.py
latticex/rosetta/rtt/ops/variable_scope.py
latticex/rosetta/rtt/ops/variables.py
latticex/rosetta/rtt/utils/__init__.py
latticex/rosetta/rtt/utils/common.py
latticex/rosetta/secure/__init__.py
latticex/rosetta/secure/client/__init__.py
latticex/rosetta/secure/client/secure_session.py
latticex/rosetta/secure/data/__init__.py
latticex/rosetta/secure/data/ops/__init__.py
latticex/rosetta/secure/data/ops/readers.py
latticex/rosetta/secure/decorator/__init__.py
latticex/rosetta/secure/decorator/secure_arithmetic_ops_.py
latticex/rosetta/secure/decorator/secure_base_.py
latticex/rosetta/secure/decorator/secure_compare_ops_.py
latticex/rosetta/secure/decorator/secure_io_ops_.py
latticex/rosetta/secure/decorator/secure_logic_ops_.py
latticex/rosetta/secure/decorator/secure_logical_ops_.py
latticex.rosetta-0.3.0.dist-info/LICENSE
latticex.rosetta-0.3.0.dist-info/METADATA
latticex.rosetta-0.3.0.dist-info/WHEEL
latticex.rosetta-0.3.0.dist-info/top_level.txt
latticex.rosetta-0.3.0.dist-info/RECORD
