Metadata-Version: 2.1
Name: latticex.rosetta
Version: 0.3.0
Summary: Rosetta is an open source privacy-preserving machine learning framework.
Home-page: https://github.com/LatticeX-Foundation/Rosetta
Author: LatticeX Foundation
Author-email: rosetta_dev@protonmail.com
License: LGPLv3
Platform: UNKNOWN
Classifier: License :: OSI Approved :: GNU General Public License v3 or later (GPLv3+)
Classifier: Programming Language :: Python
Classifier: Programming Language :: Python :: 3
Classifier: Programming Language :: Python :: 3.6
Classifier: Programming Language :: Python :: Implementation :: CPython
Classifier: Programming Language :: Python :: Implementation :: PyPy
Requires-Python: >=3.6.0
Requires-Dist: tensorflow
Requires-Dist: numpy
Requires-Dist: pandas
